{
  "results": [
    {
      "username": "md_takrimul",
      "name": "TUKHLIFUL \ud83e\udd85 SuperIntent \ud83c\udfaf\u00a0Zetarium",
      "bio": "\ud83c\udf0d Life is a path; the Hereafter is the goal.\n\ud83d\udd4b Seeking Allah\u2019s pleasure and peace.\n\ud83e\udd32 Life is worship; death is a new start.",
      "text": "Projects that focus on real connection and long-term vision stnd out in Web3. Konnex is doing exactly that by bringing users and innovation together in one ecosstem.\nLooking forward to what's next for \n@konnex_world\n \ud83d\udd17\n#Konnex #Crypto #Web3Community",
      "tweet_id": "2036381837627740670",
      "followers": 109,
      "is_verified": false,
      "twitter_url": "https://x.com/md_takrimul/status/2036381837627740670",
      "created_at": "Tue Mar 24 09:57:18 +0000 2026",
      "hours_ago": 0.1
    },
    {
      "username": "0xSibyl",
      "name": "Sibyl \u25af",
      "bio": "Software Developer | Web3 Bounty Hunter | Game Dev Hobbyist",
      "text": "I\u2019m looking to take on a new software development gig in web3.\n\nI\u2019m a dev with a solid background in Web and Game Development and I\u2019m ready to jump into a team building cool things in the decentralized space.\n\nIf your team is hiring builders or needs contract help, let's talk.",
      "tweet_id": "2036378181633188320",
      "followers": 663,
      "is_verified": false,
      "twitter_url": "https://x.com/0xSibyl/status/2036378181633188320",
      "created_at": "Tue Mar 24 09:42:47 +0000 2026",
      "hours_ago": 0.3
    },
    {
      "username": "x_Gate33",
      "name": "gate33.eth",
      "bio": "\ud83e\udd1dHiring platform with 100% verified companies\n\ud83d\udeab Against fraud: real vacancies, secure environment\n\ud83d\ude80 Distinctive features",
      "text": "\ud83d\udd25 NEW OPPORTUNITY: Senior Associate, CDD Operations at OKX\n\n\ud83d\ude80 OKX is hiring!\n\nCheck out the details in the card below \ud83d\udc47\n\u2705 Verified by Gate33\n\n\ud83d\udd17 Apply Here: https://t.co/zrFIOue0jG\n\n#Gate33 #Web3 #CryptoJobs #Blockchain #OKX https://t.co/dO8E7Yd1H2",
      "tweet_id": "2036367635927965708",
      "followers": 405,
      "is_verified": true,
      "twitter_url": "https://x.com/x_Gate33/status/2036367635927965708",
      "created_at": "Tue Mar 24 09:00:52 +0000 2026",
      "hours_ago": 1.0
    },
    {
      "username": "FlexWorkPro",
      "name": "Vico-The Remote Plug\u26a1",
      "bio": "10+ years of digital secrets. \ud83d\udd75\ufe0f\u200d\u2642\ufe0f Helping you secure 2026 Remote USD roles + AI wealth paths. High-value leads you won\u2019t find on Linkedin or elsewhere.\ud83d\udcbb\ud83e\udd47",
      "text": "Any experienced motion designer that is good with web3 related web ads banners motion graphics?\n\nDrop a comment with your POW. follow and open your DM,  so that i can message you if it fits what i am looking for. Thank you\n\n#motiondesign #motiongraphics #designer #hiring",
      "tweet_id": "2036362568999080318",
      "followers": 141,
      "is_verified": true,
      "twitter_url": "https://x.com/FlexWorkPro/status/2036362568999080318",
      "created_at": "Tue Mar 24 08:40:44 +0000 2026",
      "hours_ago": 1.3
    },
    {
      "username": "khanhlinhbn1992",
      "name": "Linh Nguy\u1ec5n",
      "bio": "",
      "text": "DTelecom is not just a technology project, but a telecommunications industry endeavor. If you are a fan of Web3 technology or simply looking for a flexible and cost-effective telecommunications solution, this is definitely a project worth following.@dtelecom",
      "tweet_id": "2036355294339768712",
      "followers": 36,
      "is_verified": false,
      "twitter_url": "https://x.com/khanhlinhbn1992/status/2036355294339768712",
      "created_at": "Tue Mar 24 08:11:50 +0000 2026",
      "hours_ago": 1.8
    },
    {
      "username": "vibeymonki",
      "name": "vibeymonki",
      "bio": "Researching decentralized banking primitives & DePIN\nCross-chain wallets \u2022 systems thinking \u2022 main: @vibeymonk \u2022 \ud83c\udf92",
      "text": "@142C_ Thank you, I really appreciate it. I am looking for 25 long-term holders right now. I have identified myself in the Telegram chat with my house address, WhatsApp number, and LinkedIn profile. I want to build something that compounds and is ingrained in the decentralized web3 ethos. I would really appreciate it if you could help me push things better because I could see that you have a huge following. Let me know how we could collab.",
      "tweet_id": "2036346683378810991",
      "followers": 1313,
      "is_verified": true,
      "twitter_url": "https://x.com/vibeymonki/status/2036346683378810991",
      "created_at": "Tue Mar 24 07:37:37 +0000 2026",
      "hours_ago": 2.4
    },
    {
      "username": "Bossjob_Web3",
      "name": "Bossjob - Web3",
      "bio": "Largest AI job search platform in the world and recruitment leader of the web3 industry.\nWebsite:https://t.co/uekTD4eRNO  Telegram:https://t.co/s4LrExHMky",
      "text": "Skip the commute. Build from anywhere. \ud83c\udfe0\ud83c\udf0d\n\nWeb3 is all about freedom, and today\u2019s Bossjob Daily Picks prove it. Weex is officially hiring for 5 high-impact roles\u2014all 100% Remote.\n\nTop Roles Open Now: \n1\ufe0f\u20e3 PM/Supervisor: https://t.co/5kSj17a2oD\n2\ufe0f\u20e3 HR Specialist: https://t.co/dlsbvSDDIy\n3\ufe0f\u20e3 DevOps: https://t.co/dcPl0OUiMe\n4\ufe0f\u20e3 Content Review: https://t.co/HsfAA7cXhE\n5\ufe0f\u20e3 Quant Strategy: https://t.co/b862rHjBRC\n\n\ud83d\udcb0 Salary: Negotiable & Competitive \n\ud83d\udccd Location: Remote (Your couch, a cafe, or the beach",
      "tweet_id": "2036341112705785897",
      "followers": 504,
      "is_verified": true,
      "twitter_url": "https://x.com/Bossjob_Web3/status/2036341112705785897",
      "created_at": "Tue Mar 24 07:15:29 +0000 2026",
      "hours_ago": 2.7
    },
    {
      "username": "Hex_Trust",
      "name": "Hex Trust",
      "bio": "Regulated institutional digital asset markets services, custody & staking for builders, investors and service providers\n\nThe Leader in Digital Asset Solutions",
      "text": "\"Regulation is the product.\" \ud83c\udfdb\ufe0f Our CEO & co-founder Alessio Quaglini @onchainpanini spoke with @SCMPNews on why Hong Kong is winning the global race for #Web3 hub status. In 2026, institutional capital isn't looking for \"regulatory ease\" - it\u2019s looking for regulatory clarity.\n\nThe Insights: \u2705 Superconnector Edge: HK is the premier bridge between global markets and the fastest-growing on-chain activity in Asia. \u2705 Institutional Liquidity: While the US leads in ETFs, HK is the agile leader for tok",
      "tweet_id": "2036337470787174722",
      "followers": 13694,
      "is_verified": true,
      "twitter_url": "https://x.com/Hex_Trust/status/2036337470787174722",
      "created_at": "Tue Mar 24 07:01:01 +0000 2026",
      "hours_ago": 3.0
    },
    {
      "username": "satyaXBT",
      "name": "satyaxbt",
      "bio": "Just a guy trying to keep up with AI, tech & Web3 \u2022 Sharing personal insight and professionally shitposting",
      "text": "you're complaining about dead airdrops while web3 teams are aggressively hiring.\n\nambassador program 7-day deadlines, $5K reff bounty and more\n\nhere are the roles open today:\n\n@glider_fi is looking for Glider Ambassadors\n\u2023 early access, rewards, work with the core team\n\u2023 applications close in one week\nhttps://t.co/YPB4fZae7U\n\n--\n@miraclechain just launched their ambassador program\n\u2023 heavy focus on content creation and community engagement\nhttps://t.co/buD7KWElmq\n\n--\n\n@SonicSVM needs Research Int",
      "tweet_id": "2036315573827805534",
      "followers": 27932,
      "is_verified": true,
      "twitter_url": "https://x.com/satyaXBT/status/2036315573827805534",
      "created_at": "Tue Mar 24 05:34:00 +0000 2026",
      "hours_ago": 4.4
    },
    {
      "username": "CassianBla",
      "name": "Cassian Blackwood",
      "bio": "The journey is the destination.",
      "text": "If you\u2019re looking for innovation in Web3, keep your eyes on @CNPYNetwork \ud83d\udc40\nThe potential here is just getting started.",
      "tweet_id": "2036313958072877562",
      "followers": 0,
      "is_verified": false,
      "twitter_url": "https://x.com/CassianBla/status/2036313958072877562",
      "created_at": "Tue Mar 24 05:27:35 +0000 2026",
      "hours_ago": 4.5
    },
    {
      "username": "DeeRealLina",
      "name": "Lina \ud83c\udf2c",
      "bio": "Digital Creator & Web3 Advocate \u2022 Crypto Enthusiast \u2022 Ambassador for @Concordium || @LitrBull || Kol for @BingXOfficial || @Bitgetwallet|| \u2022 Contributor @Avax",
      "text": "Are looking for a way to turn your Web3 activity into something that actually pays?\n\nSequoia Protocol is opening its ambassador program, offering rewards in $SEQ and USDT for creators and active community members who contribute and stay consistent.\n\nIt caught my attention because it goes beyond just posting. The focus on real contribution and growth makes it more than a typical ambassador role.\n\nPersonally, I see this as a chance to create content that simplifies the protocol, helps more users u",
      "tweet_id": "2036312820216635414",
      "followers": 21363,
      "is_verified": true,
      "twitter_url": "https://x.com/DeeRealLina/status/2036312820216635414",
      "created_at": "Tue Mar 24 05:23:03 +0000 2026",
      "hours_ago": 4.6
    },
    {
      "username": "CryptoAsmi",
      "name": "Crypto Asmi",
      "bio": "Web3 Developer | Airdrop Hunter | Crypto Influencer | Sharing alpha, insights & opportunities | DM for collabs",
      "text": "Binance is hiring! Check out the current job openings and find the role that best suits your skills.\nApply here:\n\ud83d\udd17 https://t.co/e9pGrwvtfx\n\n#Binance\u202f#CryptoJobs #Web3 #Hiring #Careers @Cryptoasmi",
      "tweet_id": "2036306770625483105",
      "followers": 13506,
      "is_verified": false,
      "twitter_url": "https://x.com/CryptoAsmi/status/2036306770625483105",
      "created_at": "Tue Mar 24 04:59:01 +0000 2026",
      "hours_ago": 5.0
    },
    {
      "username": "Raj1606",
      "name": "Raj \ud83c\udf4a,\ud83d\udc8a",
      "bio": "",
      "text": "@CoinexEU Super excited for #CoinExAlphaNight! \ud83c\udf03 Paris Blockchain Week (PBW) is the perfect place to dive deep into the future of Web3. Joining a global exchange like CoinEx is a no-brainer for anyone looking for a user-friendly and secure way to trade.@Singergst @gstsinger1",
      "tweet_id": "2036305653397070076",
      "followers": 304,
      "is_verified": false,
      "twitter_url": "https://x.com/Raj1606/status/2036305653397070076",
      "created_at": "Tue Mar 24 04:54:35 +0000 2026",
      "hours_ago": 5.1
    },
    {
      "username": "DigitalSouth12",
      "name": "Digital South Trust",
      "bio": "South India's No: 1 Blockchain Education Trust - By 2030, we aim to educate 100 million Indians about blockchain.",
      "text": "$15T payments giant Visa is hiring crypto and blockchain engineers as it continues expanding into digital assets.\n\n#Crypto #Blockchain #Web3 #DigitalAssets #Fintech #Payments #TechJobs https://t.co/IjfZx1y4kw",
      "tweet_id": "2036301207220920385",
      "followers": 125,
      "is_verified": true,
      "twitter_url": "https://x.com/DigitalSouth12/status/2036301207220920385",
      "created_at": "Tue Mar 24 04:36:55 +0000 2026",
      "hours_ago": 5.4
    },
    {
      "username": "Nwam_bugo",
      "name": "Ifeanyichukwu",
      "bio": "Web3 Researcher | Trader",
      "text": "The future of finance isn\u2019t just being built, it\u2019s being scaled. \ud83d\ude80\n\n@Binance is hiring for 350+ roles globally! From AI and Web3 engineering to compliance and growth marketing.\nJoin: https://t.co/4HviAmME34\n\n#Binance #Web3Jobs #Crypto #Hiring #TechCareers https://t.co/mWUvlgAwW2",
      "tweet_id": "2036295403390259294",
      "followers": 147,
      "is_verified": false,
      "twitter_url": "https://x.com/Nwam_bugo/status/2036295403390259294",
      "created_at": "Tue Mar 24 04:13:51 +0000 2026",
      "hours_ago": 5.8
    },
    {
      "username": "zumur6607",
      "name": "\uaa8e Airdrop $XAGE",
      "bio": "\ud83d\udccdEarth | Tweets are my own \ud83d\ude0e\nFollow back to back \ud83d\udd01\n\nBuilding connections.\nFollow back to back | Let\u2019s grow \ud83d\ude80",
      "text": "Everyone is looking for the next big airdrop \ud83d\udc40\n\nMeanwhile @River4fun dropping $1000+ opportunity for FREE \ud83d\ude31\n\nNo costNo riskJust simple tasks \u2705\n\nAlready listed on Binance \ud83d\udfe2\n\nI joined. Are you in? \ud83d\udc47https://t.co/Zw7LOi8Ggy\n\n#CryptoAirdrop #Web3",
      "tweet_id": "2036277299872670195",
      "followers": 310,
      "is_verified": false,
      "twitter_url": "https://x.com/zumur6607/status/2036277299872670195",
      "created_at": "Tue Mar 24 03:01:55 +0000 2026",
      "hours_ago": 7.0
    },
    {
      "username": "SEABWofficial",
      "name": "Southeast Asia Blockchain Week",
      "bio": "\u2728 SEABW: Showcasing the future of Web3 in Southeast Asia\n\ud83c\udf10 #SEABW2026 May 20-21, 2026\n\ud83d\udc65 Hosted by @0xShardLab x @hashed_official",
      "text": "\ud83d\udce2\u00a0The SEABW 2026 stage is open for applications.\n\nWe are looking for the voices leading the conversation.\n\nFrom regulatory frameworks and institutional adoption to tokenization, stablecoins, AI agents, and base layer infrastructure.\n\nIf you are pushing Web3 forward in Southeast Asia, the stage is yours.\n\nMay 20\u201321. True Icon Hall, Bangkok. #SEABW2026\n\nSubmit speaker application via Quick Links on our website. \n\ud83d\udd17\u00a0https://t.co/R8NPqdO4Aa",
      "tweet_id": "2036276820589551931",
      "followers": 5104,
      "is_verified": false,
      "twitter_url": "https://x.com/SEABWofficial/status/2036276820589551931",
      "created_at": "Tue Mar 24 03:00:00 +0000 2026",
      "hours_ago": 7.0
    },
    {
      "username": "MinhArteWeb3",
      "name": "MinhArte",
      "bio": "Web3 Content Creator\nTwitch Partner (22K followers) | Youtube\nFounder @BigoDAOWeb3\nReal players. Real community. Real content.",
      "text": "New week starting.\n\nWe keep pushing, always looking for real opportunities.\n\nWeb3 is still there. You just need to know where to look.\n\nStill real people. Still real community.\n\nLet\u2019s go. https://t.co/hcKOHsBsGc",
      "tweet_id": "2036258564281405737",
      "followers": 3585,
      "is_verified": true,
      "twitter_url": "https://x.com/MinhArteWeb3/status/2036258564281405737",
      "created_at": "Tue Mar 24 01:47:28 +0000 2026",
      "hours_ago": 8.2
    },
    {
      "username": "_Web3Central",
      "name": "Web3Central",
      "bio": "We\u2019re building the home screen for Web3.\nDEXs, perps, tools, bridges all in one click.",
      "text": "There is this bro who opens different tabs on chrome looking for the link to bridges like @RelayProtocol , @JumperExchange and the likes when he can just head straight to web3central.\n\nNeatly curated web3 bridges. All in a single interphase",
      "tweet_id": "2036229244469043460",
      "followers": 88,
      "is_verified": false,
      "twitter_url": "https://x.com/_Web3Central/status/2036229244469043460",
      "created_at": "Mon Mar 23 23:50:57 +0000 2026",
      "hours_ago": 10.2
    },
    {
      "username": "slepkmer",
      "name": "helcia \ud83e\udece",
      "bio": "fortune seekers struggling from poverty.\nPart of the @DataHaven_xyz community \ud83e\udece",
      "text": "Robots hiring robots @konnex_world : Negotiate contracts, license AI on-demand, execute physically, settle trustlessly in stablecoins. PoPW ensures proof. This is the bridge from digital Web3 to real-world trillions. $KNX massive potential. $KNX  #Tech",
      "tweet_id": "2036223912204443904",
      "followers": 68,
      "is_verified": false,
      "twitter_url": "https://x.com/slepkmer/status/2036223912204443904",
      "created_at": "Mon Mar 23 23:29:46 +0000 2026",
      "hours_ago": 10.5
    },
    {
      "username": "EveyNFT",
      "name": "Evey \ud83d\udc9c | Matrica Labs",
      "bio": "Partnerships & Customer Support at @MatricaLabs & @dmdotfun | Content Creator  | @SuperteamTalent Scout",
      "text": "\ud83d\udcdd@Covalent_HQ is hiring!\n\nCovalent is building the data infrastructure layer for Web3, helping developers and institutions make sense of onchain data at scale.\n\nOpen roles:\n\n\u00bb Product & Engineering\nSenior Software Engineer (Streaming Data Pipeline) \u2013 Remote\nGeneral Application \u2013 Burnaby (Full-time)\n\n\u00bb GTM\nEcosystem Growth Specialist (Streaming API) \u2013 Remote (Contract)\n\nIf you\u2019re into data, infra and multichain ecosystems, this is a strong team to look into.\n\n\ud83d\udc49 Link to apply in the comments",
      "tweet_id": "2036221657728127481",
      "followers": 15385,
      "is_verified": true,
      "twitter_url": "https://x.com/EveyNFT/status/2036221657728127481",
      "created_at": "Mon Mar 23 23:20:49 +0000 2026",
      "hours_ago": 10.7
    },
    {
      "username": "artrenoirs",
      "name": "artrenoirs",
      "bio": "Yadai",
      "text": "More like people have subconsciously limited web3 to airdrop and forget that the inflow to yield bearing protocols have increased over the years.\n\nSure, alts are down bad but people are looking for yields\nThat's the backbone of web3 tbvh, the core bone of web3 is yields.",
      "tweet_id": "2036194233799885187",
      "followers": 1215,
      "is_verified": false,
      "twitter_url": "https://x.com/artrenoirs/status/2036194233799885187",
      "created_at": "Mon Mar 23 21:31:50 +0000 2026",
      "hours_ago": 12.5
    },
    {
      "username": "Level9Labs",
      "name": "Level 9 Labs | Web3 Development",
      "bio": "Full\u2011stack app development studio delivering scalable, production\u2011ready software. #Hbar\n\nBuilding on: $ETH, $SOL, $HBAR, $SUI\n\nAffordable Full Stack Solutions.",
      "text": "The Bottom Line between Vibe Coding & a Developer:\n\nHiring a developer who knows how to use AI is like hiring a chef who knows how to use a sous-chef. \n\nHiring someone who\u2019s never coded but wants AI to do it all? That\u2019s like hiring someone who\u2019s never cooked and handing them a microwave.\n\nIf you\u2019re building anything serious, apps, games, marketplaces, trading bots, or NFT platforms, you want someone who can drive the AI, not be driven by it.\n\nAI will never replace developers; it will make us Bet",
      "tweet_id": "2036192344366870713",
      "followers": 385,
      "is_verified": true,
      "twitter_url": "https://x.com/Level9Labs/status/2036192344366870713",
      "created_at": "Mon Mar 23 21:24:20 +0000 2026",
      "hours_ago": 12.6
    },
    {
      "username": "MSTCrypto_1",
      "name": "MST Crypto Global",
      "bio": "MST Token \u2014 BEP-20 on BNB Smart Chain | Pre-sale LIVE at $0.005 | +20% Early Bird Bonus | 7% Referral Rewards | Open-source | Join now: https://t.co/Dd1WKL1tTa",
      "text": "Want to earn crypto while building a Web3 project? \ud83d\ude80 MST Token is recruiting! We're hiring marketers, content creators &amp; social media managers. Quick application, fast review, real MST rewards. Apply now: https://t.co/JTiWftepGI #MST #CryptoJobs",
      "tweet_id": "2036158425026142364",
      "followers": 94,
      "is_verified": true,
      "twitter_url": "https://x.com/MSTCrypto_1/status/2036158425026142364",
      "created_at": "Mon Mar 23 19:09:33 +0000 2026",
      "hours_ago": 14.8
    },
    {
      "username": "AmeerAbdulaleem",
      "name": "Ameer\ud83c\udfad.eth",
      "bio": "Blockchain Engineer\ud83d\udc68\u200d\ud83d\udcbb building @arctosapp || ambassador @wlthxyz || Web3-enthusiast \u2728 || ActiveLy building a decentralized worLd \ud83d\ude80  \n\nEcologist\ud83d\udc9a\ud83c\udf32\ud83c\udf34",
      "text": "\ud83d\udd30HOW OPPORTUNITY FINDS BUILDERS IN WEB3\n\nThere is a fundamental shift in how careers and partnerships are built in the decentralized space. Traditional opportunity often came through formal channels, a polished resume sent to a hiring manager, or a scheduled networking event. In Web3, the dynamic is different. Opportunity doesn't arrive with a formal knock. It appears quietly in your direct messages, as a comment on your technical thread, or as a collaboration request, but only after you have la",
      "tweet_id": "2036154364176330985",
      "followers": 973,
      "is_verified": true,
      "twitter_url": "https://x.com/AmeerAbdulaleem/status/2036154364176330985",
      "created_at": "Mon Mar 23 18:53:24 +0000 2026",
      "hours_ago": 15.1
    },
    {
      "username": "x_Gate33",
      "name": "gate33.eth",
      "bio": "\ud83e\udd1dHiring platform with 100% verified companies\n\ud83d\udeab Against fraud: real vacancies, secure environment\n\ud83d\ude80 Distinctive features",
      "text": "\ud83d\udd25 NEW OPPORTUNITY: Binance Accelerator Program - Web3 AI Engineer\uff08For blockchain student\uff09\n\n\ud83d\ude80 Binance is hiring!\n\nCheck out the details in the card below \ud83d\udc47\n\u2705 Verified by Gate33\n\n\ud83d\udd17 Apply Here: https://t.co/A9Jnrdw5zS... https://t.co/tl2eOZsNre https://t.co/cJqjIupOIA",
      "tweet_id": "2036141177733255402",
      "followers": 405,
      "is_verified": true,
      "twitter_url": "https://x.com/x_Gate33/status/2036141177733255402",
      "created_at": "Mon Mar 23 18:01:01 +0000 2026",
      "hours_ago": 16.0
    },
    {
      "username": "whitee_rhinoo",
      "name": "White Rhino Marketing",
      "bio": "Stocks, Forex & Trading Community\ud83d\udcca \nFor those who see the difference between smart investing and empty promises.\nDaily information, Market discussion\ud83e\udde0",
      "text": "\ud83d\udea8 BREAKING NEWS \ud83d\udea8 \n\n$15 trillion #Visa just announced it\u2019s hiring more $XRP and crypto engineers.\n\nThe biggest players in #finance are not slowing down, they\u2019re doubling down on #blockchain \n\nFollow the #money \nThe shift is already happening \ud83d\udd25\n\n#XRPHolders #Markets #MarketUpdate #StockMarket #trading #USA #US #stocks #crypto #Altcoins #AltcoinSeason #Bullish $Trump #TRUMP #Trump #America #XRP #Powell #Ripple",
      "tweet_id": "2036127600586752293",
      "followers": 1105,
      "is_verified": true,
      "twitter_url": "https://x.com/whitee_rhinoo/status/2036127600586752293",
      "created_at": "Mon Mar 23 17:07:04 +0000 2026",
      "hours_ago": 16.9
    },
    {
      "username": "sabrina__dx",
      "name": "Sabrina",
      "bio": "recruiting @uptopsearch, contributing @cryptocanal",
      "text": "we're hiring!\n\nlooking for a product engineer in NYC for a Series A fintech\n\nyou'd be building products powering some of the fastest growing apps in web3. typescript heavy, irl only\n\ndm me if this is you",
      "tweet_id": "2036121594838278402",
      "followers": 2541,
      "is_verified": true,
      "twitter_url": "https://x.com/sabrina__dx/status/2036121594838278402",
      "created_at": "Mon Mar 23 16:43:12 +0000 2026",
      "hours_ago": 17.3
    },
    {
      "username": "famous_dyl",
      "name": "Dyl \ud83d\udd25",
      "bio": "Multi-Platinum Artist. AI Recruiting. #Hiring Now. Crypto Since 2016. #RemoteWork https://t.co/zdRaw0t19c \ud83d\udd25 \ud83d\udccdATX - From PHL \ud83e\udd85\ud83d\udd14 inventor https://t.co/x1ABnam6zq",
      "text": "Now Hiring: Remote Workers \ud83d\udcbb\ud83d\udcb0\ud83e\udef5\nPays $50-$200/hr - Many Industries:\n\n- content writers\n- social media influencers \n- tech and sales industry\n- marketing &amp; media experts\n- crypto &amp; finance experts\n- service industry workers\n- specialized roles in science\n\nLike &amp; Reply to apply! https://t.co/ka7FXFc2PZ",
      "tweet_id": "2036060681879900368",
      "followers": 91678,
      "is_verified": true,
      "twitter_url": "https://x.com/famous_dyl/status/2036060681879900368",
      "created_at": "Mon Mar 23 12:41:09 +0000 2026",
      "hours_ago": 21.3
    },
    {
      "username": "Muhd_aliyux8",
      "name": "Muhammad Aliyu",
      "bio": "crypto trader || web3 growth strategist || inter @trustchain || @Ston_FI || contributor || @unigox_global || @speed_ln",
      "text": "We\u2019re building @Unigox_ remote first team founded by a Paxful ex-co-founder. We\u2019re hiring:\n\nIndia Marketing Manager 3-5 years in Crypto/Web3\n\nB2B Sales Manager Crypto payments experience, network, AI skills.\nApply: bogdan@unigox.com | Telegram: @bgrek_i #Web3 #Hiring #Unigox",
      "tweet_id": "2035828582170132751",
      "followers": 124,
      "is_verified": false,
      "twitter_url": "https://x.com/Muhd_aliyux8/status/2035828582170132751",
      "created_at": "Sun Mar 22 21:18:52 +0000 2026",
      "hours_ago": 36.7
    }
  ],
  "count": 30,
  "scraped_at": "2026-03-24T11:00:25.873610+00:00",
  "filter": "48 hours CET",
  "rejected_48h": 69
}